kpi_dashapp_demo/__init__.py
kpi_dashapp_demo/__main__.py
kpi_dashapp_demo/app.py
kpi_dashapp_demo/builders.py
kpi_dashapp_demo/generate_dummy_data.py
kpi_dashapp_demo/helper_components.py
kpi_dashapp_demo/kpi_utils.py
kpi_dashapp_demo/style.py
kpi_dashapp_demo-0.0.1.dist-info/METADATA
kpi_dashapp_demo-0.0.1.dist-info/WHEEL
kpi_dashapp_demo-0.0.1.dist-info/top_level.txt
kpi_dashapp_demo-0.0.1.dist-info/RECORD
