Metadata-Version: 2.1
Name: kpi-dashapp-demo
Version: 0.0.1
Summary: This package is a dash application for visualization KPIs
Home-page: UNKNOWN
Author: Agbleze Linus
Author-email: UNKNOWN
License: MIT
Platform: UNKNOWN
